pluto_base/__init__.py
pluto_base/platform.py
pluto_base/provision.py
pluto_base/resource.py
pluto_base/simulator.py
pluto_base/utils/__init__.py
pluto_base/utils/captureing_value.py
pluto_base/utils/configuration.py
pluto_base/utils/resource_id.py
pluto_base-0.0.8.dist-info/LICENSE
pluto_base-0.0.8.dist-info/METADATA
pluto_base-0.0.8.dist-info/WHEEL
pluto_base-0.0.8.dist-info/RECORD
